setup.py
mdx_cloudinary/__init__.py
mdx_cloudinary/extension.py
mdx_cloudinary/tests.py
python_markdown_cloudinary.egg-info/PKG-INFO
python_markdown_cloudinary.egg-info/SOURCES.txt
python_markdown_cloudinary.egg-info/dependency_links.txt
python_markdown_cloudinary.egg-info/requires.txt
python_markdown_cloudinary.egg-info/top_level.txt