Metadata-Version: 1.1
Name: python-markdown-cloudinary
Version: 1.0.0
Summary: Markdown extension to display and manipulate images on Cloudinary.
Home-page: https://github.com/otsuka/python-markdown-cloudinary
Author: Tomohiro Otsuka
Author-email: t.otsuka@gmail.com
License: BSD License
Keywords: python,markdown,cloudinary
Platform: UNKNOWN
Classifier: Development Status :: 5 - Production/Stable
Classifier: Environment :: Web Environment
Classifier: Intended Audience :: Developers
Classifier: License :: OSI Approved :: BSD License
Classifier: Operating System :: OS Independent
Classifier: Programming Language :: Python
Classifier: Programming Language :: Python :: 3.4
Classifier: Topic :: Software Development :: Documentation
Classifier: Topic :: Software Development :: Libraries :: Python Modules
Classifier: Topic :: Text Processing :: Filters
Classifier: Topic :: Text Processing :: Markup :: HTML
